agiverse/__init__.py
agiverse/agent/__init__.py
agiverse/agent/agent.py
agiverse/agent/api.py
agiverse/agent/data.py
agiverse/agent/messaging.py
agiverse/agent/model.py
agiverse/agent/summary.py
agiverse/agent/utils.py
agiverse/agent/memory/__init__.py
agiverse/agent/memory/base.py
agiverse/agent/memory/embedding.py
agiverse/agent/memory/importance.py
agiverse/agent/memory/manager.py
agiverse/agent/memory/reflection.py
agiverse/agent/memory/storage.py
agiverse/agent/memory/working_memory.py
agiverse/agent/prompts/agent.yaml
agiverse/agent/prompts/character.yaml
agiverse/agent/prompts/summarize.yaml
agiverse/common/__init__.py
agiverse/common/const.py
agiverse/smart_building/__init__.py
agiverse/smart_building/context.py
agiverse/smart_building/smart_building.py
agiverse-0.1.8.dist-info/METADATA
agiverse-0.1.8.dist-info/WHEEL
agiverse-0.1.8.dist-info/licenses/LICENSE
agiverse-0.1.8.dist-info/RECORD
