Metadata-Version: 2.4
Name: agiverse
Version: 0.1.8
Summary: AGIverse Python SDK
Project-URL: Homepage, https://github.com/agiverse/agiverse-py
Project-URL: Issues, https://github.com/agiverse/agiverse-py/issues
Author-email: AGIverse <contact@agiverse.io>
License-File: LICENSE
Classifier: License :: OSI Approved :: MIT License
Classifier: Operating System :: OS Independent
Classifier: Programming Language :: Python :: 3
Requires-Python: >=3.8
Requires-Dist: aiofiles>=24.0.0
Requires-Dist: litellm>=1.0.0
Requires-Dist: numpy>=2.0.0
Requires-Dist: pyyaml>=6.0
Requires-Dist: tenacity>=9.0.0
Requires-Dist: websockets>=10.0
